[
    {
        "id": 1,
        "title": "Summary",
        "content": "<p>Inventive and passionate front-end focused <strong>Web Developer</strong> since 2014. <br>Responsive, semantic UI, and a11y oriented. I aim to produce, as much as possible, a pleasant, captivating and practical user experience for everyone. </p><p>Born in Lucca(IT), London based.<br>I grew up developing a marked curiosity, and empathy for nature, besides a DIY and problem-solving aptitude. </p><p>Enjoyer in interaction design, unusual interfaces, and innovative UX. Versatile, problem solver and a quick learner. Very passionate about gamification, storytelling, and aesthetics. Addicted to music, visual arts and games.</p>"
    },
    {
        "id": 2,
        "title": "Education",
        "content": "<p>Education Content</p>"
    },
    {
        "id": 3,
        "title": "Skills",
        "content": "<p>Skills Content</p>"
    },
    {
        "id": 4,
        "title": "Work Experience",
        "content": "<p>Work Content</p>"
    },
    {
        "id": 5,
        "title": "Hobbies",
        "content": "<p>Hobbies Content</p>"
    }
    
]